{
  "notepad": "notepad",
  "np": "notepad",
  "calc": "calculator",
  "calculator": "calculator",
  "word": "start winword",
  "powerpoint": "start powerpnt",
  "ppt": "start powerpnt",
  "excel": "start excel",
  "telegram": "start telegram",
  "skype": "start skype",
  "firefox": "start firefox",
  "ff": "start firefox",
  "chrome": "start chrome",
  "opera": "start opera",
  "vlc": "start vlc",
  "steam": "start steam",
  "gimp": "start gimp",
  "vscode": "code",
  "vsc": "code",
  "visual studio code": "code",
  "photoshop": "start photoshop",
  "ps": "start photoshop",
  "7zip": "start 7zip",
  "blender": "start blender",
  "wordpad": "start wordpad",
  "wp": "start wordpad"
}